melon/__init__.py
melon/app.py
melon/core.py
melon/factory.py
melon/loader.py
melon/loggers.py
melon/settings.py
melon/utils.py
melon/webdrivers.py
melon_boot-1.1.8.dist-info/LICENSE
melon_boot-1.1.8.dist-info/METADATA
melon_boot-1.1.8.dist-info/WHEEL
melon_boot-1.1.8.dist-info/top_level.txt
melon_boot-1.1.8.dist-info/RECORD
