Metadata-Version: 2.1
Name: melon-boot
Version: 1.1.8
Summary: The ui automation framework
Home-page: UNKNOWN
Author: zh_o
Author-email: isbo.zh@outlook.com
License: UNKNOWN
Platform: UNKNOWN
License-File: LICENSE
Requires-Dist: pyyaml
Requires-Dist: selenium
Requires-Dist: pytest
Requires-Dist: allure-pytest
Requires-Dist: faker
Requires-Dist: loguru
